lczerolens/__init__.py
lczerolens/backends.py
lczerolens/board.py
lczerolens/concept.py
lczerolens/constants.py
lczerolens/lens.py
lczerolens/model.py
lczerolens/concepts/__init__.py
lczerolens/concepts/material.py
lczerolens/concepts/move.py
lczerolens/concepts/threat.py
lczerolens/lenses/__init__.py
lczerolens/lenses/activation.py
lczerolens/lenses/composite.py
lczerolens/lenses/gradient.py
lczerolens/lenses/patching.py
lczerolens/lenses/lrp/__init__.py
lczerolens/lenses/lrp/lens.py
lczerolens/lenses/lrp/rules/__init__.py
lczerolens/lenses/lrp/rules/epsilon.py
lczerolens/lenses/probing/__init__.py
lczerolens/lenses/probing/lens.py
lczerolens/lenses/probing/probe.py
lczerolens/lenses/sae/__init__.py
lczerolens/lenses/sae/buffer.py
lczerolens/play/__init__.py
lczerolens/play/game.py
lczerolens/play/puzzle.py
lczerolens/play/sampling.py
lczerolens-0.3.3.dist-info/licenses/LICENSE
lczerolens-0.3.3.dist-info/METADATA
lczerolens-0.3.3.dist-info/WHEEL
lczerolens-0.3.3.dist-info/top_level.txt
lczerolens-0.3.3.dist-info/RECORD
