Metadata-Version: 2.4
Name: lczerolens
Version: 0.3.3
Summary: Interpretability for LeelaChessZero networks.
Author-email: Yoann Poupart <yoann.poupart@ens-lyon.org>
License-Expression: MIT
Project-URL: homepage, https://lczerolens.readthedocs.io/
Project-URL: documentation, https://lczerolens.readthedocs.io/
Project-URL: source, https://github.com/Xmaster6y/lczerolens
Project-URL: issues, https://github.com/Xmaster6y/lczerolens/issues
Project-URL: releasenotes, https://github.com/Xmaster6y/lczerolens/releases
Classifier: Development Status :: 3 - Alpha
Classifier: Intended Audience :: Science/Research
Classifier: Programming Language :: Python :: 3
Classifier: Programming Language :: Python :: 3.10
Classifier: Programming Language :: Python :: 3.11
Classifier: Programming Language :: Python :: 3.12
Requires-Python: >=3.10
License-File: LICENSE
Requires-Dist: datasets>=3.2.0
Requires-Dist: einops>=0.8.0
Requires-Dist: jsonlines>=4.0.0
Requires-Dist: nnsight<0.4.0,>=0.3.7
Requires-Dist: onnx2torch>=1.5.15
Requires-Dist: python-chess>=1.999
Requires-Dist: scikit-learn>=1.6.1
Requires-Dist: tensordict>=0.6.2
Requires-Dist: typing-extensions>=4.12.2
Provides-Extra: viz
Requires-Dist: matplotlib>=3.10.0; extra == "viz"
Provides-Extra: backends
Requires-Dist: v-lczero-bindings>=0.31.2; extra == "backends"
Dynamic: license-file
